omlabs/VerticalSplitScale.py
omlabs/__init__.py
omlabs/helpers.py
omlabs/m6toolbox.py
omlabs/om4common.py
omlabs/om4parser.py
omlabs/om4plotting.py
omlabs/catalogs/OM4_catalog_dora.yml
omlabs/catalogs/OM4_catalog_gfdl.yml
omlabs/catalogs/OM4p125_catalog_dora.yml
omlabs/catalogs/OM4p125_catalog_gfdl.yml
omlabs/catalogs/OM4p125_catalog_testing.yml
omlabs/catalogs/OM4p5_catalog_gfdl.yml
omlabs/catalogs/OM4p5_catalog_testing.yml
omlabs/catalogs/OMIP2_catalog_generic.yml
omlabs/catalogs/OMIP2_catalog_gfdl.yml
omlabs/catalogs/obs_catalog_dora.yml
omlabs/catalogs/obs_catalog_gaea.yml
omlabs/catalogs/obs_catalog_generic.yml
omlabs/catalogs/obs_catalog_gfdl.yml
omlabs/catalogs/obs_catalog_testing.yml
omlabs/diags/__init__.py
omlabs/diags/acc_drake/__init__.py
omlabs/diags/acc_drake/acc_timeseries.py
omlabs/diags/avail/__init__.py
omlabs/diags/avail/avail.py
omlabs/diags/depth_time_salinity_drift/__init__.py
omlabs/diags/depth_time_salinity_drift/depth_time_salinity_drift.py
omlabs/diags/depth_time_temperature_drift/__init__.py
omlabs/diags/depth_time_temperature_drift/depth_time_temperature_drift.py
omlabs/diags/enso/__init__.py
omlabs/diags/enso/enso.py
omlabs/diags/generic_annual_bias_1x1deg/__init__.py
omlabs/diags/generic_annual_bias_1x1deg/generic_annual_bias_1x1deg.py
omlabs/diags/generic_depth_time_drift/__init__.py
omlabs/diags/generic_depth_time_drift/generic_depth_time_drift.py
omlabs/diags/generic_section_transport/__init__.py
omlabs/diags/generic_section_transport/generic_section_transport.py
omlabs/diags/generic_yz_annual_bias_1x1deg/__init__.py
omlabs/diags/generic_yz_annual_bias_1x1deg/generic_yz_annual_bias_1x1deg.py
omlabs/diags/heat_transport/__init__.py
omlabs/diags/heat_transport/heat_transport.py
omlabs/diags/moc/__init__.py
omlabs/diags/moc/moc.py
omlabs/diags/moc/plotting/__init__.py
omlabs/diags/moc/plotting/plot_rho.py
omlabs/diags/moc/plotting/plot_z.py
omlabs/diags/seaice/__init__.py
omlabs/diags/seaice/seaice.py
omlabs-3.0.0a3.dist-info/LICENSE.txt
omlabs-3.0.0a3.dist-info/METADATA
omlabs-3.0.0a3.dist-info/WHEEL
omlabs-3.0.0a3.dist-info/top_level.txt
omlabs-3.0.0a3.dist-info/RECORD
