Metadata-Version: 2.1
Name: omlabs
Version: 3.0.0a3
Summary: Analysis Routines for GFDL Ocean Models
Author-email: John Krasting <john.krasting@noaa.gov>
License: Software code created by U.S. Government employees is not subject to copyright in the United States (17 U.S.C. §105).
Project-URL: homepage, https://github.com/jkrasting/omlabs
Project-URL: documentation, https://github.com/jkrasting/omlabs
Project-URL: repository, https://github.com/jkrasting/omlabs
Keywords: oceanography,mom,mom6,model,ocean
Classifier: Development Status :: 3 - Alpha
Classifier: Intended Audience :: Science/Research
Classifier: Topic :: Scientific/Engineering
Classifier: License :: Public Domain
Classifier: Programming Language :: Python :: 3.8
Classifier: Programming Language :: Python :: 3.9
Classifier: Programming Language :: Python :: 3.10
Classifier: Programming Language :: Python :: 3.11
Requires-Python: >=3.8
License-File: LICENSE.txt
Requires-Dist: importlib-metadata <5.0.0
Requires-Dist: cartopy
Requires-Dist: cmip-basins
Requires-Dist: gsw
Requires-Dist: intake
Requires-Dist: numpy
Requires-Dist: matplotlib
Requires-Dist: palettable
Requires-Dist: regionmask
Requires-Dist: scipy
Requires-Dist: static-downsampler
Requires-Dist: xarray
Requires-Dist: xcompare
Requires-Dist: xesmf
Requires-Dist: xgcm
Requires-Dist: xoverturning
Requires-Dist: xwavelet
Provides-Extra: test
Requires-Dist: pytest ; extra == 'test'
